<annotation>
	<folder>Images</folder>
	<filename>2128.jpg</filename>
	<path>C:\Users\satyabrata_kundu\Desktop\TensorFlow_Preparations\Second_Iterations\Images\2128.jpg</path>
	<source>
		<database>Unknown</database>
	</source>
	<size>
		<width>1438</width>
		<height>1438</height>
		<depth>1</depth>
	</size>
	<segmented>0</segmented>
	<object>
		<name>gun</name>
		<pose>Unspecified</pose>
		<truncated>0</truncated>
		<difficult>0</difficult>
		<bndbox>
			<xmin>296</xmin>
			<ymin>286</ymin>
			<xmax>722</xmax>
			<ymax>856</ymax>
		</bndbox>
	</object>
</annotation>
