<annotation>
	<folder>10april</folder>
	<filename>2293.jpg</filename>
	<path>D:\Softwares\softwares\10april\2293.jpg</path>
	<source>
		<database>Unknown</database>
	</source>
	<size>
		<width>1438</width>
		<height>1438</height>
		<depth>1</depth>
	</size>
	<segmented>0</segmented>
	<object>
		<name>gun</name>
		<pose>Unspecified</pose>
		<truncated>0</truncated>
		<difficult>0</difficult>
		<bndbox>
			<xmin>746</xmin>
			<ymin>453</ymin>
			<xmax>1117</xmax>
			<ymax>1027</ymax>
		</bndbox>
	</object>
</annotation>
