<annotation>
	<folder>Images</folder>
	<filename>1578.jpg</filename>
	<path>C:\Users\satyabrata_kundu\Desktop\TensorFlow_Preparations\Fifth_Iterations\Labelling_Images\Images\1578.jpg</path>
	<source>
		<database>Unknown</database>
	</source>
	<size>
		<width>1080</width>
		<height>607</height>
		<depth>3</depth>
	</size>
	<segmented>0</segmented>
	<object>
		<name>gun</name>
		<pose>Unspecified</pose>
		<truncated>0</truncated>
		<difficult>0</difficult>
		<bndbox>
			<xmin>186</xmin>
			<ymin>75</ymin>
			<xmax>907</xmax>
			<ymax>575</ymax>
		</bndbox>
	</object>
</annotation>
